jschemalite/__init__.py
jschemalite/jschemalite.py
jschemalite/mongodb.py
jschemalite-0.1.post2.dist-info/LICENSE.txt
jschemalite-0.1.post2.dist-info/METADATA
jschemalite-0.1.post2.dist-info/WHEEL
jschemalite-0.1.post2.dist-info/top_level.txt
jschemalite-0.1.post2.dist-info/RECORD
