Metadata-Version: 2.1
Name: jschemalite
Version: 0.1.post2
Summary: JSON Schema Lite
Home-page: https://www.github.com/krishauser/jschemalite
Author: Kris Hauser
Author-email: hauser.kris@gmail.com
License: Apache 2.0
Platform: UNKNOWN
License-File: LICENSE.txt
